{
  "audiovisual_files": {
    "bc90c2db-898c-434d-80d9-414e10c47dd8": {
      "label": "Guantanamera de Tomás Gutiérrez Alea y Juan Carlos Tabio (1995) ",
      "is_offline": false,
      "file_type": "Video",
      "file_url": "https://m.ok.ru/video/2289159637649",
      "duration": 5837
    }
  },
  "auto_generate_web_page": true,
  "label": "Guantanamera de Tomás Gutiérrez Alea y Juan Carlos Tabio (1995) ",
  "created_at": "2025-07-28T19:14:47.261Z",
  "created_by": "jackDeVry",
  "updated_at": "2025-07-28T19:14:47.261Z",
  "updated_by": "jackDeVry"
}